[
  {
    "model": "catalog.category",
    "pk": 1,
    "fields": {
      "name": "Смартфоны",
      "description": "Смартфон - это мобильное устройство, в котором сочетается функционал сотового телефона и компьютера."
    }
  },
  {
    "model": "catalog.category",
    "pk": 2,
    "fields": {
      "name": "Смарт-часы",
      "description": "Смарт-часы могут быть полезны любым пользователям, которые хотят обладать компактным устройством, обеспечивающим возможность коммутации со смартфоном"
    }
  },
  {
    "model": "catalog.category",
    "pk": 3,
    "fields": {
      "name": "Сотовые телефоны",
      "description": "Несомненным преимуществом этого вида средств обмена голосовой и текстовой информацией является компактность"
    }
  }
]